{
  "week": "2026-05-W04",
  "date": "2026-05-18",
  "agencies": {
    "과학기술정보통신부": {
      "5월18일(월)": [
        "▲10:30 1차관 아시아올림피아드 개회식(부경대학교)",
        "▲14:00 1차관 한국과학영재학교 간담회(부산 한국과학영재학교)"
      ],
      "5월19일(화)": [
        "▲10:30 1차관 핀란드 고용경제부 장관 면담(여의도 IFC)"
      ],
      "5월20일(수)": [
        "▲1차관 13:00 26년도 연구현장 소통을 위한 이공계 대학 방문(강원대학교)",
        "▲14:00 부총리 본부장 국무회의"
      ],
      "5월21일(목)": [
        "▲10:00 1차관 공공연구성과 확산을 위한 전문조직 출범식(피스앤파크 컨벤션)"
      ],
      "5월22일(금)": [
        "▲특이일정없음"
      ]
    },
    "방송미디어통신위원회": {
      "5월18일(월)": [
        "▲10:00 위원장 광주지역 현장방문(광주)"
      ],
      "5월19일(화)": [
        "▲특이일정없음"
      ],
      "5월20일(수)": [
        "▲14:00 위원장 국무회의(서울)"
      ],
      "5월21일(목)": [
        "▲특이일정없음"
      ],
      "5월22일(금)": [
        "▲10:00 상임위원 차관회의(서울)"
      ]
    },
    "금융위원회": {
      "5월 17일(일)": [
        "※「가계부채 점검 회의」개최(18일 조간)"
      ],
      "5월 18일(월)": [
        "▲14:00 위원장 국민성장펀드 성과 점검 세미나(산업은행)",
        "※'청년 모두를 위한 재무상담' 시범 사업 실시(석간)",
        "※국민성장펀드 성과점검 및 발전방향 세미나(14:00)",
        "※증권사 유동성 관리 강화 등 「금융투자업규정·시행세칙」개정 추진(19일 조간)"
      ],
      "5월 19일(화)": [],
      "5월 20일(수)": [
        "▲14:00 부위원장 증선위 정례회의(정부서울청사)",
        "※주가조작·회계부정 신고포상금 제도개선 및 회계부정 제재 강화를 위한 자본시장법·외부감사법 시행령 국무회의 통과(배포시)"
      ],
      "5월 21일(목)": [
        "▲10:00 위원장 기자간담회(정부서울청사)",
        "▲15:00 위원장 해운업-금융권 간담회(손해보험협회)",
        "※금융위원장-출입기자단 간담회(14:00)",
        "※중동상황 피해업종(해운업) 관련 산업-금융권 간담회(15:00)"
      ],
      "5월 22일(금)": [
        "▲10:00 위원장 주간업무회의(정부서울청사)",
        "▲10:00 부위원장 AI 보안 위협 대응 관련 금융권 간담회(정부서울청사)"
      ],
      "5월 24일(일)": [
        "※고성능 AI 보안 위협 대응 관련 금융권 간담회 실시(25일 조간)"
      ]
    },
    "금융감독원": {
      "5월17일(일)": [
        "※「가계부채 점검 회의」 개최(조간)",
        "※2025년 전자금융업 영업실적(조간)"
      ],
      "5월18일(월)": [
        "※2025년 국내 증권회사 해외점포 영업실적(석간)",
        "※부동산 PF 수수료 운영실태 점검 간담회 개최(10:00)",
        "※금융회사의 사전예방적 대응역량강화를 위한 2026년 보안취약점 신고포상제(「버그바운티」) 실시(조간)",
        "※증권사 유동성 관리 강화 등 「금융투자업규정·시행세칙」 개정 추진(조간)"
      ],
      "5월19일(화)": [
        "▲10:00 주례 임원회의(비공개)",
        "※금융감독원, 제2차 소비자위험대응협의회 개최(석간)",
        "※최근 민원사례로 알아보는 '실손의료보험' 관련 유의사항(조간)"
      ],
      "5월20일(수)": [
        "※2026.1분기 국내은행 영업실적[잠정](석간)",
        "※2025년 우리나라 퇴직연금 투자 백서(조간)",
        "※2026년도 제61회 공인회계사 제2차시험 응시원서 접수결과(배포시)",
        "※주가조작·회계부정 신고포상금 제도 개선 및 회계부정 제재 강화를 위한 자본시장법·외부감사법 시행령 국무회의 통과(배포시)"
      ],
      "5월21일(목)": [
        "※2025년 국내은행의 해외점포 경영현황 및 현지화지표 평가결과(석간)",
        "※AI·디지털 서비스 확대 및 IT사고 관련 소비자 보호 강화를 위한 금융회사 CCO 간담회 개최(11:00)",
        "※주요 민원사례로 알아보는 ETF투자시 소비자 유의사항(조간)"
      ],
      "5월22일(금)": [
        "※금융감독원-금융투자협회, 자산운용업계 내부통제 강화를 위한 준법감시인 워크숍 개최(13:30)"
      ]
    },
    "행정안전부": {
      "5월 18일(월)": [
        "▲11:00 제46주년 5·18민주화운동 기념식 참석(광주)"
      ],
      "5월 19일(화)": [
        "▲10:00 고유가 피해지원금 2차 지급 현장방문(서울 영등포구 문래동주민센터 등)",
        "▲14:00 제4회 중앙지방 정책협의회 주재(서울청사 19층 대회의실)",
        "▲16:00 제7기 국가기록관리 위원회 위촉식(서울청사 12층 영상회의실)"
      ],
      "5월 20일(수)": [
        "▲10:00 공명선거 관계장관회의 참석(서울청사)",
        "▲11:20 제9회 전국동시지방선거 대국민 담화문 발표(서울청사 본관 브리핑실)",
        "▲14:00 국무회의"
      ],
      "5월 22일(금)": [
        "▲10:00 2026 OECD 열린정부 국제심포지엄(웨스틴조선 서울)",
        "▲14:00 제33회 방재의 날 기념식 개최(서울청사 별관 국제회의실)"
      ]
    }
  }
}